biscuit/__init__.py
biscuit/__main__.py
biscuit/api/__init__.py
biscuit/api/base.py
biscuit/api/commands.py
biscuit/api/editors.py
biscuit/api/endpoint.py
biscuit/api/logger.py
biscuit/api/notifications.py
biscuit/api/README.md
biscuit/api/releases.py
biscuit/api/theme.py
biscuit/api/views.py
biscuit/app.py
biscuit/binder.py
biscuit/cli/__init__.py
biscuit/cli/cli.py
biscuit/cli/editor.py
biscuit/cli/extensions.py
biscuit/cli/git.py
biscuit/cli/README.md
biscuit/commands.py
biscuit/common/__init__.py
biscuit/common/actionset.py
biscuit/common/classdrill.py
biscuit/common/codicon.py
biscuit/common/fixedstack.py
biscuit/common/games/__init__.py
biscuit/common/games/game.py
biscuit/common/games/gamebase.py
biscuit/common/games/gameoflife.py
biscuit/common/games/minesweeper.py
biscuit/common/games/pong.py
biscuit/common/games/ttt.py
biscuit/common/games/whoops.py
biscuit/common/helpers.py
biscuit/common/io.py
biscuit/common/menu/__init__.py
biscuit/common/menu/checkable.py
biscuit/common/menu/command.py
biscuit/common/menu/menu.py
biscuit/common/menu/separator.py
biscuit/common/minclosestdict.py
biscuit/common/notifications/__init__.py
biscuit/common/notifications/manager.py
biscuit/common/notifications/notification.py
biscuit/common/palette/__init__.py
biscuit/common/palette/item.py
biscuit/common/palette/palette.py
biscuit/common/palette/searchbar.py
biscuit/common/sysinfo.py
biscuit/common/textindex.py
biscuit/common/textutils.py
biscuit/common/ui/__init__.py
biscuit/common/ui/bubble.py
biscuit/common/ui/buttons.py
biscuit/common/ui/buttonsentry.py
biscuit/common/ui/closables.py
biscuit/common/ui/demo/dnd.py
biscuit/common/ui/demo/dpi_demo.py
biscuit/common/ui/demo/window_demo.py
biscuit/common/ui/hintedentry.py
biscuit/common/ui/icons.py
biscuit/common/ui/labels.py
biscuit/common/ui/linklabel.py
biscuit/common/ui/native.py
biscuit/common/ui/scrollableframe.py
biscuit/common/ui/scrollbar.py
biscuit/common/ui/shortcut.py
biscuit/common/ui/tree.py
biscuit/config.py
biscuit_api-2.99.4.dist-info/entry_points.txt
biscuit_api-2.99.4.dist-info/LICENSE.md
biscuit_api-2.99.4.dist-info/METADATA
biscuit_api-2.99.4.dist-info/WHEEL
biscuit_api-2.99.4.dist-info/RECORD
