Metadata-Version: 2.1
Name: biscuit-api
Version: 2.99.4
Summary: The uncompromising code editor
License: MIT
Author: Billy
Author-email: billydevbusiness@gmail.com
Requires-Python: >=3.10,<4.0
Classifier: License :: OSI Approved :: MIT License
Classifier: Programming Language :: Python :: 3
Classifier: Programming Language :: Python :: 3.10
Classifier: Programming Language :: Python :: 3.11
Classifier: Programming Language :: Python :: 3.12
Requires-Dist: GitPython (>=3.1.43,<4.0.0)
Requires-Dist: Pillow (>=10.3.0,<11.0.0)
Requires-Dist: Pygments (>=2.18.0,<3.0.0)
Requires-Dist: chardet (>=5.2.0,<6.0.0)
Requires-Dist: click (>=8.1.7,<9.0.0)
Requires-Dist: filetype (>=1.2.0,<2.0.0)
Requires-Dist: google-generativeai (>=0.5.4,<0.6.0)
Requires-Dist: hintedtext (>=0.6.0,<0.7.0)
Requires-Dist: mistune (>=3.0.2,<4.0.0)
Requires-Dist: psutil (>=5.9.8,<6.0.0)
Requires-Dist: ptyprocess (>=0.7.0,<0.8.0) ; sys_platform == "linux"
Requires-Dist: pyperclip (>=1.8.2,<2.0.0)
Requires-Dist: python-tkdnd (>=0.2.1,<0.3.0)
Requires-Dist: pywinpty (>=2.0.13,<3.0.0) ; sys_platform == "win32"
Requires-Dist: requests (>=2.32.2,<3.0.0)
Requires-Dist: sortedcontainers (>=2.4.0,<3.0.0)
Requires-Dist: sv-ttk (>=2.6.0,<3.0.0)
Requires-Dist: tarts (>=0.12.0,<0.13.0)
Requires-Dist: tkextrafont (>=0.6.3,<0.7.0)
Requires-Dist: tkinterweb (>=3.23.9,<4.0.0)
Requires-Dist: toml (>=0.10.2,<0.11.0)
Requires-Dist: watchdog (>=4.0.1,<5.0.0)
